{
    "label": {
        "id": 261,
        "name": "Fishing Point",
        "icon": "https://act-webstatic.hoyoverse.com/map_manage/20240726/052bbb288d4f3245166908367aa8ccd8_465260317346550977.png",
        "parent_id": 232,
        "depth": 2,
        "node_type": 2,
        "jump_type": 0,
        "jump_target_id": 0,
        "wiki_jump_url": "",
        "display_priority": 0,
        "children": [],
        "activity_page_label": 27,
        "area_page_label": [],
        "is_all_area": true,
        "default_show": false,
        "ch_ext": "",
        "sort": 0,
        "area_label_list": [
            5,
            6,
            5,
            6
        ],
        "ext_attr_list": [],
        "recommend_route_list": [],
        "point_count": 0,
        "alias_name": "\u9493\u9c7c\u70b9",
        "item_id": 0,
        "rec_refresh_hour": 0,
        "tips": ""
    },
    "point": [
        {
            "id": 80612,
            "label_id": 261,
            "x_pos": -10474.625,
            "y_pos": 2162.125,
            "author_name": "\u9ec4\u660f\u89e6\u52a8\u9ece\u660e",
            "ctime": "2024-11-22 14:03:44",
            "display_state": 1,
            "area_id": 11,
            "ext_attrs": "{}",
            "ext_attrs_map": {},
            "z_level": 0,
            "icon_sign": 0,
            "point_group": null
        },
        {
            "id": 80611,
            "label_id": 261,
            "x_pos": -10870.875,
            "y_pos": 2321.875,
            "author_name": "\u9ec4\u660f\u89e6\u52a8\u9ece\u660e",
            "ctime": "2024-11-22 14:03:43",
            "display_state": 1,
            "area_id": 11,
            "ext_attrs": "{}",
            "ext_attrs_map": {},
            "z_level": 0,
            "icon_sign": 0,
            "point_group": null
        },
        {
            "id": 80610,
            "label_id": 261,
            "x_pos": -11057.875,
            "y_pos": 2524.25,
            "author_name": "\u9ec4\u660f\u89e6\u52a8\u9ece\u660e",
            "ctime": "2024-11-22 14:03:43",
            "display_state": 1,
            "area_id": 11,
            "ext_attrs": "{}",
            "ext_attrs_map": {},
            "z_level": 0,
            "icon_sign": 1,
            "point_group": {
                "group_id": 158,
                "floor_id": 212
            }
        },
        {
            "id": 80609,
            "label_id": 261,
            "x_pos": -11078.25,
            "y_pos": 2814,
            "author_name": "\u9ec4\u660f\u89e6\u52a8\u9ece\u660e",
            "ctime": "2024-11-22 14:03:42",
            "display_state": 1,
            "area_id": 11,
            "ext_attrs": "{}",
            "ext_attrs_map": {},
            "z_level": 0,
            "icon_sign": 0,
            "point_group": null
        },
        {
            "id": 80608,
            "label_id": 261,
            "x_pos": -9932.625,
            "y_pos": 2660,
            "author_name": "\u9ec4\u660f\u89e6\u52a8\u9ece\u660e",
            "ctime": "2024-11-22 14:03:45",
            "display_state": 1,
            "area_id": 11,
            "ext_attrs": "{}",
            "ext_attrs_map": {},
            "z_level": 0,
            "icon_sign": 0,
            "point_group": null
        },
        {
            "id": 80607,
            "label_id": 261,
            "x_pos": -10915.625,
            "y_pos": 3942.25,
            "author_name": "\u9ec4\u660f\u89e6\u52a8\u9ece\u660e",
            "ctime": "2024-11-22 14:03:48",
            "display_state": 1,
            "area_id": 11,
            "ext_attrs": "{}",
            "ext_attrs_map": {},
            "z_level": 0,
            "icon_sign": 0,
            "point_group": null
        },
        {
            "id": 80606,
            "label_id": 261,
            "x_pos": -10681,
            "y_pos": 3508.125,
            "author_name": "\u9ec4\u660f\u89e6\u52a8\u9ece\u660e",
            "ctime": "2024-11-22 14:03:47",
            "display_state": 1,
            "area_id": 11,
            "ext_attrs": "{}",
            "ext_attrs_map": {},
            "z_level": 0,
            "icon_sign": 0,
            "point_group": null
        },
        {
            "id": 80605,
            "label_id": 261,
            "x_pos": -10325,
            "y_pos": 3368.375,
            "author_name": "\u9ec4\u660f\u89e6\u52a8\u9ece\u660e",
            "ctime": "2024-11-22 14:03:46",
            "display_state": 1,
            "area_id": 11,
            "ext_attrs": "{}",
            "ext_attrs_map": {},
            "z_level": 0,
            "icon_sign": 0,
            "point_group": null
        },
        {
            "id": 80604,
            "label_id": 261,
            "x_pos": -10471.25,
            "y_pos": 3213.25,
            "author_name": "\u9ec4\u660f\u89e6\u52a8\u9ece\u660e",
            "ctime": "2024-11-22 14:03:45",
            "display_state": 1,
            "area_id": 11,
            "ext_attrs": "{}",
            "ext_attrs_map": {},
            "z_level": 0,
            "icon_sign": 0,
            "point_group": null
        },
        {
            "id": 80603,
            "label_id": 261,
            "x_pos": -9400.125,
            "y_pos": 5150.25,
            "author_name": "\u9ec4\u660f\u89e6\u52a8\u9ece\u660e",
            "ctime": "2024-11-22 14:03:48",
            "display_state": 1,
            "area_id": 11,
            "ext_attrs": "{}",
            "ext_attrs_map": {},
            "z_level": 0,
            "icon_sign": 1,
            "point_group": {
                "group_id": 144,
                "floor_id": 186
            }
        },
        {
            "id": 80602,
            "label_id": 261,
            "x_pos": -8427,
            "y_pos": 4400,
            "author_name": "\u9ec4\u660f\u89e6\u52a8\u9ece\u660e",
            "ctime": "2024-11-22 14:03:48",
            "display_state": 1,
            "area_id": 11,
            "ext_attrs": "{}",
            "ext_attrs_map": {},
            "z_level": 0,
            "icon_sign": 1,
            "point_group": {
                "group_id": 145,
                "floor_id": 188
            }
        },
        {
            "id": 68555,
            "label_id": 261,
            "x_pos": -5116.25,
            "y_pos": 1250,
            "author_name": "\u9ec4\u660f\u89e6\u52a8\u9ece\u660e",
            "ctime": "2024-11-22 14:03:49",
            "display_state": 1,
            "area_id": 8,
            "ext_attrs": "{}",
            "ext_attrs_map": {},
            "z_level": 0,
            "icon_sign": 0,
            "point_group": null
        },
        {
            "id": 66513,
            "label_id": 261,
            "x_pos": -3050.500205827173,
            "y_pos": 1417.9959715566747,
            "author_name": "\u51ac\u536b",
            "ctime": "2024-07-31 16:58:35",
            "display_state": 1,
            "area_id": 2,
            "ext_attrs": "{}",
            "ext_attrs_map": {},
            "z_level": 0,
            "icon_sign": 0,
            "point_group": null
        },
        {
            "id": 66512,
            "label_id": 261,
            "x_pos": -2468.49320770327,
            "y_pos": 431.499496444585,
            "author_name": "\u51ac\u536b",
            "ctime": "2024-07-31 16:58:35",
            "display_state": 1,
            "area_id": 2,
            "ext_attrs": "{}",
            "ext_attrs_map": {},
            "z_level": 0,
            "icon_sign": 0,
            "point_group": null
        },
        {
            "id": 66511,
            "label_id": 261,
            "x_pos": -1853.48867950545,
            "y_pos": 456.9919431133476,
            "author_name": "\u51ac\u536b",
            "ctime": "2024-07-31 16:58:33",
            "display_state": 1,
            "area_id": 2,
            "ext_attrs": "{}",
            "ext_attrs_map": {},
            "z_level": 0,
            "icon_sign": 0,
            "point_group": null
        },
        {
            "id": 56284,
            "label_id": 261,
            "x_pos": -4162,
            "y_pos": -833.75,
            "author_name": "FTFuture",
            "ctime": "2025-03-03 10:38:30",
            "display_state": 1,
            "area_id": 8,
            "ext_attrs": "{}",
            "ext_attrs_map": {},
            "z_level": 0,
            "icon_sign": 0,
            "point_group": null
        },
        {
            "id": 56283,
            "label_id": 261,
            "x_pos": -3657.5,
            "y_pos": -941.5,
            "author_name": "FTFuture",
            "ctime": "2024-01-19 10:08:41",
            "display_state": 1,
            "area_id": 8,
            "ext_attrs": "{}",
            "ext_attrs_map": {},
            "z_level": 0,
            "icon_sign": 0,
            "point_group": null
        },
        {
            "id": 56282,
            "label_id": 261,
            "x_pos": -4573,
            "y_pos": -634.75,
            "author_name": "FTFuture",
            "ctime": "2024-01-19 10:08:40",
            "display_state": 1,
            "area_id": 8,
            "ext_attrs": "{}",
            "ext_attrs_map": {},
            "z_level": 0,
            "icon_sign": 0,
            "point_group": null
        },
        {
            "id": 56281,
            "label_id": 261,
            "x_pos": -4180.5,
            "y_pos": -51,
            "author_name": "FTFuture",
            "ctime": "2024-01-19 10:08:41",
            "display_state": 1,
            "area_id": 8,
            "ext_attrs": "{}",
            "ext_attrs_map": {},
            "z_level": 0,
            "icon_sign": 0,
            "point_group": null
        },
        {
            "id": 54581,
            "label_id": 261,
            "x_pos": -5613.499279604892,
            "y_pos": -2072.7487411114607,
            "author_name": "\u51ac\u536b",
            "ctime": "2024-01-19 10:08:32",
            "display_state": 1,
            "area_id": 8,
            "ext_attrs": "{}",
            "ext_attrs_map": {},
            "z_level": 0,
            "icon_sign": 0,
            "point_group": null
        },
        {
            "id": 54580,
            "label_id": 261,
            "x_pos": -4731.249485432066,
            "y_pos": -2211.250083925903,
            "author_name": "\u51ac\u536b",
            "ctime": "2024-01-19 10:08:42",
            "display_state": 1,
            "area_id": 8,
            "ext_attrs": "{}",
            "ext_attrs_map": {},
            "z_level": 0,
            "icon_sign": 0,
            "point_group": null
        },
        {
            "id": 50430,
            "label_id": 261,
            "x_pos": -4808,
            "y_pos": -1065.75,
            "author_name": "FTFuture",
            "ctime": "2024-01-19 10:08:38",
            "display_state": 1,
            "area_id": 8,
            "ext_attrs": "{}",
            "ext_attrs_map": {},
            "z_level": 0,
            "icon_sign": 0,
            "point_group": null
        },
        {
            "id": 50429,
            "label_id": 261,
            "x_pos": -5217,
            "y_pos": -903.5,
            "author_name": "FTFuture",
            "ctime": "2024-01-19 10:08:37",
            "display_state": 1,
            "area_id": 8,
            "ext_attrs": "{}",
            "ext_attrs_map": {},
            "z_level": 0,
            "icon_sign": 0,
            "point_group": null
        },
        {
            "id": 50428,
            "label_id": 261,
            "x_pos": -5481.5,
            "y_pos": -694.5,
            "author_name": "FTFuture",
            "ctime": "2024-01-19 10:08:37",
            "display_state": 1,
            "area_id": 8,
            "ext_attrs": "{}",
            "ext_attrs_map": {},
            "z_level": 0,
            "icon_sign": 0,
            "point_group": null
        },
        {
            "id": 50427,
            "label_id": 261,
            "x_pos": -5370.5,
            "y_pos": -421.75,
            "author_name": "FTFuture",
            "ctime": "2024-01-19 10:08:36",
            "display_state": 1,
            "area_id": 8,
            "ext_attrs": "{}",
            "ext_attrs_map": {},
            "z_level": 0,
            "icon_sign": 0,
            "point_group": null
        },
        {
            "id": 50426,
            "label_id": 261,
            "x_pos": -5009.25,
            "y_pos": -1423.5,
            "author_name": "FTFuture",
            "ctime": "2024-01-19 10:08:31",
            "display_state": 1,
            "area_id": 8,
            "ext_attrs": "{}",
            "ext_attrs_map": {},
            "z_level": 0,
            "icon_sign": 0,
            "point_group": null
        },
        {
            "id": 50425,
            "label_id": 261,
            "x_pos": -5688,
            "y_pos": 118.75,
            "author_name": "FTFuture",
            "ctime": "2024-01-19 10:08:26",
            "display_state": 1,
            "area_id": 8,
            "ext_attrs": "{}",
            "ext_attrs_map": {},
            "z_level": 0,
            "icon_sign": 0,
            "point_group": null
        },
        {
            "id": 50424,
            "label_id": 261,
            "x_pos": -4662.5,
            "y_pos": -1216.75,
            "author_name": "FTFuture",
            "ctime": "2024-01-19 10:08:39",
            "display_state": 1,
            "area_id": 8,
            "ext_attrs": "{}",
            "ext_attrs_map": {},
            "z_level": 0,
            "icon_sign": 0,
            "point_group": null
        },
        {
            "id": 50423,
            "label_id": 261,
            "x_pos": -5098.5,
            "y_pos": -331.5,
            "author_name": "FTFuture",
            "ctime": "2024-01-19 10:08:24",
            "display_state": 1,
            "area_id": 8,
            "ext_attrs": "{}",
            "ext_attrs_map": {},
            "z_level": 0,
            "icon_sign": 0,
            "point_group": null
        },
        {
            "id": 46512,
            "label_id": 261,
            "x_pos": -6886.5,
            "y_pos": 2211.25,
            "author_name": "FTFuture",
            "ctime": "2024-01-19 10:08:35",
            "display_state": 1,
            "area_id": 4,
            "ext_attrs": "{}",
            "ext_attrs_map": {},
            "z_level": 0,
            "icon_sign": 0,
            "point_group": null
        },
        {
            "id": 43365,
            "label_id": 261,
            "x_pos": -5572.25,
            "y_pos": 2518.5,
            "author_name": "Slothw",
            "ctime": "2023-01-18 03:00:58",
            "display_state": 1,
            "area_id": 4,
            "ext_attrs": "",
            "ext_attrs_map": {},
            "z_level": 0,
            "icon_sign": 0,
            "point_group": null
        },
        {
            "id": 38144,
            "label_id": 261,
            "x_pos": -4937,
            "y_pos": 4811.5,
            "author_name": "\u747e\u747e\u4e36",
            "ctime": "2024-12-24 17:15:34",
            "display_state": 1,
            "area_id": 4,
            "ext_attrs": "",
            "ext_attrs_map": {},
            "z_level": 0,
            "icon_sign": 0,
            "point_group": null
        },
        {
            "id": 38143,
            "label_id": 261,
            "x_pos": -4909,
            "y_pos": 4291.5,
            "author_name": "\u747e\u747e\u4e36",
            "ctime": "2022-09-28 02:21:50",
            "display_state": 1,
            "area_id": 4,
            "ext_attrs": "",
            "ext_attrs_map": {},
            "z_level": 0,
            "icon_sign": 0,
            "point_group": null
        },
        {
            "id": 30465,
            "label_id": 261,
            "x_pos": -3120.355532322341,
            "y_pos": 1913.4016633594683,
            "author_name": "\u6d3b\u8dc3\u4e4b\u9c7c",
            "ctime": "2024-01-19 10:08:20",
            "display_state": 1,
            "area_id": 4,
            "ext_attrs": "",
            "ext_attrs_map": {},
            "z_level": 0,
            "icon_sign": 0,
            "point_group": null
        },
        {
            "id": 30464,
            "label_id": 261,
            "x_pos": -4314.499514123746,
            "y_pos": 2623.2495421944113,
            "author_name": "\u6d3b\u8dc3\u4e4b\u9c7c",
            "ctime": "2022-08-24 03:21:52",
            "display_state": 1,
            "area_id": 4,
            "ext_attrs": "",
            "ext_attrs_map": {},
            "z_level": 0,
            "icon_sign": 0,
            "point_group": null
        },
        {
            "id": 30463,
            "label_id": 261,
            "x_pos": -3598.750971752508,
            "y_pos": 2838.0005493667068,
            "author_name": "\u6d3b\u8dc3\u4e4b\u9c7c",
            "ctime": "2024-01-19 10:08:27",
            "display_state": 1,
            "area_id": 4,
            "ext_attrs": "",
            "ext_attrs_map": {},
            "z_level": 0,
            "icon_sign": 0,
            "point_group": null
        },
        {
            "id": 30462,
            "label_id": 261,
            "x_pos": -3610.999222597994,
            "y_pos": 3003.9998168777647,
            "author_name": "\u6d3b\u8dc3\u4e4b\u9c7c",
            "ctime": "2025-02-17 11:30:08",
            "display_state": 1,
            "area_id": 4,
            "ext_attrs": "",
            "ext_attrs_map": {},
            "z_level": 0,
            "icon_sign": 0,
            "point_group": null
        },
        {
            "id": 30461,
            "label_id": 261,
            "x_pos": -3398.2946034401057,
            "y_pos": 3340.2101709137514,
            "author_name": "\u6d3b\u8dc3\u4e4b\u9c7c",
            "ctime": "2022-08-24 03:21:52",
            "display_state": 1,
            "area_id": 4,
            "ext_attrs": "",
            "ext_attrs_map": {},
            "z_level": 0,
            "icon_sign": 0,
            "point_group": null
        },
        {
            "id": 30460,
            "label_id": 261,
            "x_pos": -3071.093093890242,
            "y_pos": 3618.9121928880177,
            "author_name": "\u6d3b\u8dc3\u4e4b\u9c7c",
            "ctime": "2022-08-24 03:21:52",
            "display_state": 1,
            "area_id": 4,
            "ext_attrs": "",
            "ext_attrs_map": {},
            "z_level": 0,
            "icon_sign": 0,
            "point_group": null
        },
        {
            "id": 30459,
            "label_id": 261,
            "x_pos": -3300.845911972514,
            "y_pos": 4014.70898061922,
            "author_name": "\u6d3b\u8dc3\u4e4b\u9c7c",
            "ctime": "2022-08-24 03:21:52",
            "display_state": 1,
            "area_id": 4,
            "ext_attrs": "",
            "ext_attrs_map": {},
            "z_level": 0,
            "icon_sign": 0,
            "point_group": null
        },
        {
            "id": 20055,
            "label_id": 261,
            "x_pos": 1638.5,
            "y_pos": 8759.328499201292,
            "author_name": "",
            "ctime": "2021-10-23 10:00:37",
            "display_state": 1,
            "area_id": 3,
            "ext_attrs": "",
            "ext_attrs_map": {},
            "z_level": 0,
            "icon_sign": 0,
            "point_group": null
        },
        {
            "id": 18686,
            "label_id": 261,
            "x_pos": 2040,
            "y_pos": 8354.5,
            "author_name": "",
            "ctime": "2021-10-21 10:31:43",
            "display_state": 1,
            "area_id": 3,
            "ext_attrs": "",
            "ext_attrs_map": {},
            "z_level": 0,
            "icon_sign": 0,
            "point_group": null
        },
        {
            "id": 17694,
            "label_id": 261,
            "x_pos": 3327,
            "y_pos": 6754,
            "author_name": "",
            "ctime": "2021-09-07 00:08:38",
            "display_state": 1,
            "area_id": 3,
            "ext_attrs": "",
            "ext_attrs_map": {},
            "z_level": 0,
            "icon_sign": 0,
            "point_group": null
        },
        {
            "id": 17693,
            "label_id": 261,
            "x_pos": 3212,
            "y_pos": 5569.5,
            "author_name": "",
            "ctime": "2021-09-07 00:08:29",
            "display_state": 1,
            "area_id": 3,
            "ext_attrs": "",
            "ext_attrs_map": {},
            "z_level": 0,
            "icon_sign": 0,
            "point_group": null
        },
        {
            "id": 17692,
            "label_id": 261,
            "x_pos": 2951,
            "y_pos": 4871.5,
            "author_name": "",
            "ctime": "2021-09-07 00:08:26",
            "display_state": 1,
            "area_id": 3,
            "ext_attrs": "",
            "ext_attrs_map": {},
            "z_level": 0,
            "icon_sign": 0,
            "point_group": null
        },
        {
            "id": 17691,
            "label_id": 261,
            "x_pos": 3398.5,
            "y_pos": 6779,
            "author_name": "",
            "ctime": "2021-09-07 00:08:20",
            "display_state": 1,
            "area_id": 3,
            "ext_attrs": "",
            "ext_attrs_map": {},
            "z_level": 0,
            "icon_sign": 0,
            "point_group": null
        },
        {
            "id": 17690,
            "label_id": 261,
            "x_pos": 2878.5,
            "y_pos": 5907.5,
            "author_name": "",
            "ctime": "2021-09-07 00:08:12",
            "display_state": 1,
            "area_id": 3,
            "ext_attrs": "",
            "ext_attrs_map": {},
            "z_level": 0,
            "icon_sign": 0,
            "point_group": null
        },
        {
            "id": 17689,
            "label_id": 261,
            "x_pos": 1883,
            "y_pos": 5719.5,
            "author_name": "",
            "ctime": "2021-09-07 00:08:05",
            "display_state": 1,
            "area_id": 3,
            "ext_attrs": "",
            "ext_attrs_map": {},
            "z_level": 0,
            "icon_sign": 0,
            "point_group": null
        },
        {
            "id": 17688,
            "label_id": 261,
            "x_pos": 512.5,
            "y_pos": 5895.5,
            "author_name": "",
            "ctime": "2021-09-07 00:08:00",
            "display_state": 1,
            "area_id": 3,
            "ext_attrs": "",
            "ext_attrs_map": {},
            "z_level": 0,
            "icon_sign": 0,
            "point_group": null
        },
        {
            "id": 17687,
            "label_id": 261,
            "x_pos": 61,
            "y_pos": 5961.5,
            "author_name": "",
            "ctime": "2021-09-07 00:07:53",
            "display_state": 1,
            "area_id": 3,
            "ext_attrs": "",
            "ext_attrs_map": {},
            "z_level": 0,
            "icon_sign": 0,
            "point_group": null
        },
        {
            "id": 17686,
            "label_id": 261,
            "x_pos": -653,
            "y_pos": 3073,
            "author_name": "",
            "ctime": "2021-09-07 00:07:45",
            "display_state": 1,
            "area_id": 2,
            "ext_attrs": "",
            "ext_attrs_map": {},
            "z_level": 0,
            "icon_sign": 0,
            "point_group": null
        },
        {
            "id": 17685,
            "label_id": 261,
            "x_pos": -803,
            "y_pos": 1679.5,
            "author_name": "",
            "ctime": "2021-09-07 00:07:39",
            "display_state": 1,
            "area_id": 2,
            "ext_attrs": "",
            "ext_attrs_map": {},
            "z_level": 0,
            "icon_sign": 0,
            "point_group": null
        },
        {
            "id": 17684,
            "label_id": 261,
            "x_pos": -1272.5,
            "y_pos": 2178.5,
            "author_name": "",
            "ctime": "2021-09-07 00:07:34",
            "display_state": 1,
            "area_id": 2,
            "ext_attrs": "",
            "ext_attrs_map": {},
            "z_level": 0,
            "icon_sign": 0,
            "point_group": null
        },
        {
            "id": 17683,
            "label_id": 261,
            "x_pos": -2090.5,
            "y_pos": 2174,
            "author_name": "",
            "ctime": "2021-09-07 00:07:28",
            "display_state": 1,
            "area_id": 2,
            "ext_attrs": "",
            "ext_attrs_map": {},
            "z_level": 0,
            "icon_sign": 0,
            "point_group": null
        },
        {
            "id": 17682,
            "label_id": 261,
            "x_pos": -1294,
            "y_pos": 1373.5,
            "author_name": "",
            "ctime": "2021-09-07 00:07:21",
            "display_state": 1,
            "area_id": 2,
            "ext_attrs": "",
            "ext_attrs_map": {},
            "z_level": 0,
            "icon_sign": 0,
            "point_group": null
        },
        {
            "id": 17681,
            "label_id": 261,
            "x_pos": -2402,
            "y_pos": 1633,
            "author_name": "",
            "ctime": "2021-09-07 00:07:08",
            "display_state": 1,
            "area_id": 2,
            "ext_attrs": "",
            "ext_attrs_map": {},
            "z_level": 0,
            "icon_sign": 0,
            "point_group": null
        },
        {
            "id": 17680,
            "label_id": 261,
            "x_pos": -2329,
            "y_pos": 1190.5,
            "author_name": "",
            "ctime": "2021-09-07 00:07:02",
            "display_state": 1,
            "area_id": 2,
            "ext_attrs": "",
            "ext_attrs_map": {},
            "z_level": 0,
            "icon_sign": 0,
            "point_group": null
        },
        {
            "id": 17679,
            "label_id": 261,
            "x_pos": -1757,
            "y_pos": 954.5,
            "author_name": "",
            "ctime": "2021-09-07 00:06:55",
            "display_state": 1,
            "area_id": 2,
            "ext_attrs": "",
            "ext_attrs_map": {},
            "z_level": 0,
            "icon_sign": 0,
            "point_group": null
        },
        {
            "id": 17678,
            "label_id": 261,
            "x_pos": -1881.5,
            "y_pos": 789.5,
            "author_name": "",
            "ctime": "2021-09-07 00:06:49",
            "display_state": 1,
            "area_id": 2,
            "ext_attrs": "",
            "ext_attrs_map": {},
            "z_level": 0,
            "icon_sign": 0,
            "point_group": null
        },
        {
            "id": 17677,
            "label_id": 261,
            "x_pos": -1162,
            "y_pos": 1011,
            "author_name": "",
            "ctime": "2021-09-07 00:06:43",
            "display_state": 1,
            "area_id": 2,
            "ext_attrs": "",
            "ext_attrs_map": {},
            "z_level": 0,
            "icon_sign": 0,
            "point_group": null
        },
        {
            "id": 17676,
            "label_id": 261,
            "x_pos": -141.5,
            "y_pos": 1335,
            "author_name": "\u5f25\u60a6",
            "ctime": "2024-01-19 10:08:28",
            "display_state": 1,
            "area_id": 1,
            "ext_attrs": "",
            "ext_attrs_map": {},
            "z_level": 0,
            "icon_sign": 0,
            "point_group": null
        },
        {
            "id": 17675,
            "label_id": 261,
            "x_pos": -1198,
            "y_pos": 507,
            "author_name": "",
            "ctime": "2021-09-07 00:06:29",
            "display_state": 1,
            "area_id": 2,
            "ext_attrs": "",
            "ext_attrs_map": {},
            "z_level": 0,
            "icon_sign": 0,
            "point_group": null
        },
        {
            "id": 17674,
            "label_id": 261,
            "x_pos": -491,
            "y_pos": 621.5,
            "author_name": "",
            "ctime": "2021-09-07 00:06:22",
            "display_state": 1,
            "area_id": 1,
            "ext_attrs": "",
            "ext_attrs_map": {},
            "z_level": 0,
            "icon_sign": 0,
            "point_group": null
        },
        {
            "id": 17673,
            "label_id": 261,
            "x_pos": 312,
            "y_pos": 38,
            "author_name": "",
            "ctime": "2021-09-07 00:06:16",
            "display_state": 1,
            "area_id": 1,
            "ext_attrs": "",
            "ext_attrs_map": {},
            "z_level": 0,
            "icon_sign": 0,
            "point_group": null
        },
        {
            "id": 17672,
            "label_id": 261,
            "x_pos": 65,
            "y_pos": 263.5,
            "author_name": "",
            "ctime": "2021-09-07 00:06:10",
            "display_state": 1,
            "area_id": 1,
            "ext_attrs": "",
            "ext_attrs_map": {},
            "z_level": 0,
            "icon_sign": 0,
            "point_group": null
        },
        {
            "id": 17671,
            "label_id": 261,
            "x_pos": -816,
            "y_pos": -564,
            "author_name": "",
            "ctime": "2021-09-07 00:06:01",
            "display_state": 1,
            "area_id": 1,
            "ext_attrs": "",
            "ext_attrs_map": {},
            "z_level": 0,
            "icon_sign": 0,
            "point_group": null
        },
        {
            "id": 17670,
            "label_id": 261,
            "x_pos": -868,
            "y_pos": -177,
            "author_name": "",
            "ctime": "2021-09-07 00:05:55",
            "display_state": 1,
            "area_id": 1,
            "ext_attrs": "",
            "ext_attrs_map": {},
            "z_level": 0,
            "icon_sign": 0,
            "point_group": null
        },
        {
            "id": 17669,
            "label_id": 261,
            "x_pos": 584.5,
            "y_pos": -435,
            "author_name": "\u5f25\u60a6",
            "ctime": "2024-01-19 10:08:23",
            "display_state": 1,
            "area_id": 1,
            "ext_attrs": "",
            "ext_attrs_map": {},
            "z_level": 0,
            "icon_sign": 0,
            "point_group": null
        },
        {
            "id": 17668,
            "label_id": 261,
            "x_pos": 529,
            "y_pos": 470.5,
            "author_name": "",
            "ctime": "2021-09-09 10:07:45",
            "display_state": 1,
            "area_id": 1,
            "ext_attrs": "",
            "ext_attrs_map": {},
            "z_level": 0,
            "icon_sign": 0,
            "point_group": null
        }
    ]
}