{
    "label": {
        "id": 613,
        "name": "Saurian Claw Succulent",
        "icon": "https://act-webstatic.hoyoverse.com/map_manage/20241014/8613846a348c997a6ee119d7b7aca936_9152503678963694001.png",
        "parent_id": 10,
        "depth": 2,
        "node_type": 2,
        "jump_type": 0,
        "jump_target_id": 0,
        "wiki_jump_url": "",
        "display_priority": 0,
        "children": [],
        "activity_page_label": 0,
        "area_page_label": [],
        "is_all_area": false,
        "default_show": false,
        "ch_ext": "",
        "sort": 0,
        "area_label_list": [],
        "ext_attr_list": [],
        "recommend_route_list": [],
        "point_count": 0,
        "alias_name": "",
        "item_id": 101250,
        "rec_refresh_hour": 0,
        "tips": ""
    },
    "point": [
        {
            "id": 80244,
            "label_id": 613,
            "x_pos": -11043.36940927412,
            "y_pos": 2494.7933859371824,
            "author_name": "EricMonlye",
            "ctime": "2024-11-23 23:00:39",
            "display_state": 1,
            "area_id": 11,
            "ext_attrs": "{}",
            "ext_attrs_map": {},
            "z_level": 0,
            "icon_sign": 0,
            "point_group": null
        },
        {
            "id": 80197,
            "label_id": 613,
            "x_pos": -11014.625,
            "y_pos": 2564.25,
            "author_name": "\u6069\u666e\u7984",
            "ctime": "2024-11-23 23:00:31",
            "display_state": 1,
            "area_id": 11,
            "ext_attrs": "{}",
            "ext_attrs_map": {},
            "z_level": 0,
            "icon_sign": 0,
            "point_group": null
        },
        {
            "id": 80196,
            "label_id": 613,
            "x_pos": -10984.5,
            "y_pos": 2561.75,
            "author_name": "\u6069\u666e\u7984",
            "ctime": "2024-11-23 23:00:24",
            "display_state": 1,
            "area_id": 11,
            "ext_attrs": "{}",
            "ext_attrs_map": {},
            "z_level": 0,
            "icon_sign": 0,
            "point_group": null
        },
        {
            "id": 80195,
            "label_id": 613,
            "x_pos": -10992.5,
            "y_pos": 2539.25,
            "author_name": "\u6069\u666e\u7984",
            "ctime": "2024-11-23 23:00:50",
            "display_state": 1,
            "area_id": 11,
            "ext_attrs": "{}",
            "ext_attrs_map": {},
            "z_level": 0,
            "icon_sign": 0,
            "point_group": null
        },
        {
            "id": 80194,
            "label_id": 613,
            "x_pos": -10994.875,
            "y_pos": 2539.5,
            "author_name": "\u6069\u666e\u7984",
            "ctime": "2024-11-23 23:00:51",
            "display_state": 1,
            "area_id": 11,
            "ext_attrs": "{}",
            "ext_attrs_map": {},
            "z_level": 0,
            "icon_sign": 0,
            "point_group": null
        },
        {
            "id": 80193,
            "label_id": 613,
            "x_pos": -11005.75,
            "y_pos": 2506.25,
            "author_name": "\u6069\u666e\u7984",
            "ctime": "2024-11-23 23:00:25",
            "display_state": 1,
            "area_id": 11,
            "ext_attrs": "{}",
            "ext_attrs_map": {},
            "z_level": 0,
            "icon_sign": 0,
            "point_group": null
        },
        {
            "id": 80192,
            "label_id": 613,
            "x_pos": -11004,
            "y_pos": 2503.375,
            "author_name": "\u6069\u666e\u7984",
            "ctime": "2024-11-23 23:00:33",
            "display_state": 1,
            "area_id": 11,
            "ext_attrs": "{}",
            "ext_attrs_map": {},
            "z_level": 0,
            "icon_sign": 0,
            "point_group": null
        },
        {
            "id": 80191,
            "label_id": 613,
            "x_pos": -11098.5,
            "y_pos": 2515.75,
            "author_name": "\u6069\u666e\u7984",
            "ctime": "2024-11-23 23:00:52",
            "display_state": 1,
            "area_id": 11,
            "ext_attrs": "{}",
            "ext_attrs_map": {},
            "z_level": 0,
            "icon_sign": 1,
            "point_group": {
                "group_id": 158,
                "floor_id": 213
            }
        },
        {
            "id": 80190,
            "label_id": 613,
            "x_pos": -11085,
            "y_pos": 2523.25,
            "author_name": "\u6069\u666e\u7984",
            "ctime": "2024-11-23 23:00:55",
            "display_state": 1,
            "area_id": 11,
            "ext_attrs": "{}",
            "ext_attrs_map": {},
            "z_level": 0,
            "icon_sign": 1,
            "point_group": {
                "group_id": 158,
                "floor_id": 213
            }
        },
        {
            "id": 80189,
            "label_id": 613,
            "x_pos": -11052.75,
            "y_pos": 2435.125,
            "author_name": "\u6069\u666e\u7984",
            "ctime": "2024-11-23 23:00:27",
            "display_state": 1,
            "area_id": 11,
            "ext_attrs": "{}",
            "ext_attrs_map": {},
            "z_level": 0,
            "icon_sign": 1,
            "point_group": {
                "group_id": 158,
                "floor_id": 211
            }
        },
        {
            "id": 80188,
            "label_id": 613,
            "x_pos": -11053.75,
            "y_pos": 2467,
            "author_name": "\u6069\u666e\u7984",
            "ctime": "2024-11-23 23:00:48",
            "display_state": 1,
            "area_id": 11,
            "ext_attrs": "{}",
            "ext_attrs_map": {},
            "z_level": 0,
            "icon_sign": 1,
            "point_group": {
                "group_id": 158,
                "floor_id": 211
            }
        },
        {
            "id": 80187,
            "label_id": 613,
            "x_pos": -11047.25,
            "y_pos": 2465.25,
            "author_name": "\u6069\u666e\u7984",
            "ctime": "2024-11-23 23:00:43",
            "display_state": 1,
            "area_id": 11,
            "ext_attrs": "{}",
            "ext_attrs_map": {},
            "z_level": 0,
            "icon_sign": 1,
            "point_group": {
                "group_id": 158,
                "floor_id": 211
            }
        },
        {
            "id": 80186,
            "label_id": 613,
            "x_pos": -11043.75,
            "y_pos": 2480,
            "author_name": "\u6069\u666e\u7984",
            "ctime": "2024-11-23 23:00:32",
            "display_state": 1,
            "area_id": 11,
            "ext_attrs": "{}",
            "ext_attrs_map": {},
            "z_level": 0,
            "icon_sign": 0,
            "point_group": null
        },
        {
            "id": 73158,
            "label_id": 613,
            "x_pos": -9091,
            "y_pos": 3834.25,
            "author_name": "elevenium",
            "ctime": "2024-09-05 10:57:48",
            "display_state": 1,
            "area_id": 11,
            "ext_attrs": "{}",
            "ext_attrs_map": {},
            "z_level": 0,
            "icon_sign": 0,
            "point_group": null
        },
        {
            "id": 73157,
            "label_id": 613,
            "x_pos": -8914,
            "y_pos": 3629.25,
            "author_name": "elevenium",
            "ctime": "2024-09-02 14:36:13",
            "display_state": 1,
            "area_id": 11,
            "ext_attrs": "{}",
            "ext_attrs_map": {},
            "z_level": 0,
            "icon_sign": 0,
            "point_group": null
        },
        {
            "id": 73156,
            "label_id": 613,
            "x_pos": -8913,
            "y_pos": 3634,
            "author_name": "elevenium",
            "ctime": "2024-09-02 14:36:23",
            "display_state": 1,
            "area_id": 11,
            "ext_attrs": "{}",
            "ext_attrs_map": {},
            "z_level": 0,
            "icon_sign": 0,
            "point_group": null
        },
        {
            "id": 73155,
            "label_id": 613,
            "x_pos": -9069,
            "y_pos": 3615.75,
            "author_name": "elevenium",
            "ctime": "2024-08-29 11:36:24",
            "display_state": 1,
            "area_id": 11,
            "ext_attrs": "{}",
            "ext_attrs_map": {},
            "z_level": 0,
            "icon_sign": 0,
            "point_group": null
        },
        {
            "id": 73154,
            "label_id": 613,
            "x_pos": -9068.75,
            "y_pos": 3617.5,
            "author_name": "elevenium",
            "ctime": "2024-08-29 11:36:26",
            "display_state": 1,
            "area_id": 11,
            "ext_attrs": "{}",
            "ext_attrs_map": {},
            "z_level": 0,
            "icon_sign": 0,
            "point_group": null
        },
        {
            "id": 73153,
            "label_id": 613,
            "x_pos": -9005,
            "y_pos": 3635.5,
            "author_name": "elevenium",
            "ctime": "2024-08-29 11:36:25",
            "display_state": 1,
            "area_id": 11,
            "ext_attrs": "{}",
            "ext_attrs_map": {},
            "z_level": 0,
            "icon_sign": 0,
            "point_group": null
        },
        {
            "id": 73152,
            "label_id": 613,
            "x_pos": -9009,
            "y_pos": 3629.5,
            "author_name": "elevenium",
            "ctime": "2024-08-29 11:36:25",
            "display_state": 1,
            "area_id": 11,
            "ext_attrs": "{}",
            "ext_attrs_map": {},
            "z_level": 0,
            "icon_sign": 0,
            "point_group": null
        },
        {
            "id": 73151,
            "label_id": 613,
            "x_pos": -9006.5,
            "y_pos": 3627.5,
            "author_name": "elevenium",
            "ctime": "2024-08-29 11:36:28",
            "display_state": 1,
            "area_id": 11,
            "ext_attrs": "{}",
            "ext_attrs_map": {},
            "z_level": 0,
            "icon_sign": 0,
            "point_group": null
        },
        {
            "id": 73150,
            "label_id": 613,
            "x_pos": -9026.5,
            "y_pos": 3511,
            "author_name": "elevenium",
            "ctime": "2024-08-29 11:36:23",
            "display_state": 1,
            "area_id": 11,
            "ext_attrs": "{}",
            "ext_attrs_map": {},
            "z_level": 0,
            "icon_sign": 0,
            "point_group": null
        },
        {
            "id": 73149,
            "label_id": 613,
            "x_pos": -9043.375,
            "y_pos": 3535.75,
            "author_name": "elevenium",
            "ctime": "2024-08-29 11:36:27",
            "display_state": 1,
            "area_id": 11,
            "ext_attrs": "{}",
            "ext_attrs_map": {},
            "z_level": 0,
            "icon_sign": 0,
            "point_group": null
        },
        {
            "id": 73148,
            "label_id": 613,
            "x_pos": -9045.25,
            "y_pos": 3536.5,
            "author_name": "elevenium",
            "ctime": "2024-08-29 11:36:22",
            "display_state": 1,
            "area_id": 11,
            "ext_attrs": "{}",
            "ext_attrs_map": {},
            "z_level": 0,
            "icon_sign": 0,
            "point_group": null
        },
        {
            "id": 73147,
            "label_id": 613,
            "x_pos": -9215.375,
            "y_pos": 3557,
            "author_name": "elevenium",
            "ctime": "2024-09-02 14:36:15",
            "display_state": 1,
            "area_id": 11,
            "ext_attrs": "{}",
            "ext_attrs_map": {},
            "z_level": 0,
            "icon_sign": 0,
            "point_group": null
        },
        {
            "id": 73146,
            "label_id": 613,
            "x_pos": -9212.5,
            "y_pos": 3557,
            "author_name": "elevenium",
            "ctime": "2024-09-02 14:36:10",
            "display_state": 1,
            "area_id": 11,
            "ext_attrs": "{}",
            "ext_attrs_map": {},
            "z_level": 0,
            "icon_sign": 0,
            "point_group": null
        },
        {
            "id": 73145,
            "label_id": 613,
            "x_pos": -9223.25,
            "y_pos": 3777,
            "author_name": "elevenium",
            "ctime": "2024-09-05 10:57:54",
            "display_state": 1,
            "area_id": 11,
            "ext_attrs": "{}",
            "ext_attrs_map": {},
            "z_level": 0,
            "icon_sign": 0,
            "point_group": null
        },
        {
            "id": 73144,
            "label_id": 613,
            "x_pos": -9221.75,
            "y_pos": 3782.75,
            "author_name": "elevenium",
            "ctime": "2024-09-05 10:57:50",
            "display_state": 1,
            "area_id": 11,
            "ext_attrs": "{}",
            "ext_attrs_map": {},
            "z_level": 0,
            "icon_sign": 0,
            "point_group": null
        },
        {
            "id": 73143,
            "label_id": 613,
            "x_pos": -9234.75,
            "y_pos": 3835.5,
            "author_name": "elevenium",
            "ctime": "2024-09-05 10:57:55",
            "display_state": 1,
            "area_id": 11,
            "ext_attrs": "{}",
            "ext_attrs_map": {},
            "z_level": 0,
            "icon_sign": 0,
            "point_group": null
        },
        {
            "id": 73142,
            "label_id": 613,
            "x_pos": -9236.25,
            "y_pos": 3839.25,
            "author_name": "elevenium",
            "ctime": "2024-09-05 10:57:57",
            "display_state": 1,
            "area_id": 11,
            "ext_attrs": "{}",
            "ext_attrs_map": {},
            "z_level": 0,
            "icon_sign": 0,
            "point_group": null
        },
        {
            "id": 73141,
            "label_id": 613,
            "x_pos": -9243.5,
            "y_pos": 3826.5,
            "author_name": "elevenium",
            "ctime": "2024-09-05 10:57:49",
            "display_state": 1,
            "area_id": 11,
            "ext_attrs": "{}",
            "ext_attrs_map": {},
            "z_level": 0,
            "icon_sign": 0,
            "point_group": null
        },
        {
            "id": 73140,
            "label_id": 613,
            "x_pos": -9192.5,
            "y_pos": 3820,
            "author_name": "elevenium",
            "ctime": "2024-09-05 10:57:46",
            "display_state": 1,
            "area_id": 11,
            "ext_attrs": "{}",
            "ext_attrs_map": {},
            "z_level": 0,
            "icon_sign": 0,
            "point_group": null
        },
        {
            "id": 73139,
            "label_id": 613,
            "x_pos": -9188,
            "y_pos": 3821,
            "author_name": "elevenium",
            "ctime": "2024-09-05 10:57:45",
            "display_state": 1,
            "area_id": 11,
            "ext_attrs": "{}",
            "ext_attrs_map": {},
            "z_level": 0,
            "icon_sign": 0,
            "point_group": null
        },
        {
            "id": 73138,
            "label_id": 613,
            "x_pos": -9188,
            "y_pos": 3853,
            "author_name": "elevenium",
            "ctime": "2024-09-05 10:57:54",
            "display_state": 1,
            "area_id": 11,
            "ext_attrs": "{}",
            "ext_attrs_map": {},
            "z_level": 0,
            "icon_sign": 0,
            "point_group": null
        },
        {
            "id": 73137,
            "label_id": 613,
            "x_pos": -9338.5,
            "y_pos": 3692,
            "author_name": "elevenium",
            "ctime": "2024-08-29 11:36:28",
            "display_state": 1,
            "area_id": 11,
            "ext_attrs": "{}",
            "ext_attrs_map": {},
            "z_level": 0,
            "icon_sign": 1,
            "point_group": {
                "group_id": 146,
                "floor_id": 189
            }
        },
        {
            "id": 73136,
            "label_id": 613,
            "x_pos": -9338,
            "y_pos": 3690,
            "author_name": "elevenium",
            "ctime": "2024-08-29 11:36:31",
            "display_state": 1,
            "area_id": 11,
            "ext_attrs": "{}",
            "ext_attrs_map": {},
            "z_level": 0,
            "icon_sign": 1,
            "point_group": {
                "group_id": 146,
                "floor_id": 189
            }
        },
        {
            "id": 73135,
            "label_id": 613,
            "x_pos": -9338,
            "y_pos": 3683,
            "author_name": "elevenium",
            "ctime": "2024-08-29 11:36:30",
            "display_state": 1,
            "area_id": 11,
            "ext_attrs": "{}",
            "ext_attrs_map": {},
            "z_level": 0,
            "icon_sign": 1,
            "point_group": {
                "group_id": 146,
                "floor_id": 189
            }
        },
        {
            "id": 73134,
            "label_id": 613,
            "x_pos": -9300.75,
            "y_pos": 3663.5,
            "author_name": "elevenium",
            "ctime": "2024-08-29 11:36:23",
            "display_state": 1,
            "area_id": 11,
            "ext_attrs": "{}",
            "ext_attrs_map": {},
            "z_level": 0,
            "icon_sign": 1,
            "point_group": {
                "group_id": 146,
                "floor_id": 189
            }
        },
        {
            "id": 73133,
            "label_id": 613,
            "x_pos": -9299,
            "y_pos": 3660,
            "author_name": "elevenium",
            "ctime": "2024-08-29 11:36:27",
            "display_state": 1,
            "area_id": 11,
            "ext_attrs": "{}",
            "ext_attrs_map": {},
            "z_level": 0,
            "icon_sign": 1,
            "point_group": {
                "group_id": 146,
                "floor_id": 189
            }
        },
        {
            "id": 73132,
            "label_id": 613,
            "x_pos": -9124.5,
            "y_pos": 3712.75,
            "author_name": "elevenium",
            "ctime": "2024-09-05 10:57:59",
            "display_state": 1,
            "area_id": 11,
            "ext_attrs": "{}",
            "ext_attrs_map": {},
            "z_level": 0,
            "icon_sign": 1,
            "point_group": {
                "group_id": 146,
                "floor_id": 189
            }
        },
        {
            "id": 73131,
            "label_id": 613,
            "x_pos": -9126.5,
            "y_pos": 3712,
            "author_name": "elevenium",
            "ctime": "2024-09-05 10:57:46",
            "display_state": 1,
            "area_id": 11,
            "ext_attrs": "{}",
            "ext_attrs_map": {},
            "z_level": 0,
            "icon_sign": 1,
            "point_group": {
                "group_id": 146,
                "floor_id": 189
            }
        },
        {
            "id": 73130,
            "label_id": 613,
            "x_pos": -9122,
            "y_pos": 3706.5,
            "author_name": "elevenium",
            "ctime": "2024-09-05 10:57:44",
            "display_state": 1,
            "area_id": 11,
            "ext_attrs": "{}",
            "ext_attrs_map": {},
            "z_level": 0,
            "icon_sign": 1,
            "point_group": {
                "group_id": 146,
                "floor_id": 189
            }
        },
        {
            "id": 73129,
            "label_id": 613,
            "x_pos": -9028.75,
            "y_pos": 3728,
            "author_name": "elevenium",
            "ctime": "2024-09-05 10:57:55",
            "display_state": 1,
            "area_id": 11,
            "ext_attrs": "{}",
            "ext_attrs_map": {},
            "z_level": 0,
            "icon_sign": 1,
            "point_group": {
                "group_id": 146,
                "floor_id": 189
            }
        },
        {
            "id": 73128,
            "label_id": 613,
            "x_pos": -9030.25,
            "y_pos": 3728,
            "author_name": "elevenium",
            "ctime": "2024-09-05 10:57:44",
            "display_state": 1,
            "area_id": 11,
            "ext_attrs": "{}",
            "ext_attrs_map": {},
            "z_level": 0,
            "icon_sign": 1,
            "point_group": {
                "group_id": 146,
                "floor_id": 189
            }
        },
        {
            "id": 73127,
            "label_id": 613,
            "x_pos": -9021,
            "y_pos": 3746.5,
            "author_name": "elevenium",
            "ctime": "2024-09-05 10:57:43",
            "display_state": 1,
            "area_id": 11,
            "ext_attrs": "{}",
            "ext_attrs_map": {},
            "z_level": 0,
            "icon_sign": 1,
            "point_group": {
                "group_id": 146,
                "floor_id": 189
            }
        },
        {
            "id": 73126,
            "label_id": 613,
            "x_pos": -8979.5,
            "y_pos": 3904.5,
            "author_name": "elevenium",
            "ctime": "2024-09-05 10:57:46",
            "display_state": 1,
            "area_id": 11,
            "ext_attrs": "{}",
            "ext_attrs_map": {},
            "z_level": 0,
            "icon_sign": 0,
            "point_group": null
        },
        {
            "id": 73125,
            "label_id": 613,
            "x_pos": -8975.5,
            "y_pos": 3905.5,
            "author_name": "elevenium",
            "ctime": "2024-09-05 10:57:48",
            "display_state": 1,
            "area_id": 11,
            "ext_attrs": "{}",
            "ext_attrs_map": {},
            "z_level": 0,
            "icon_sign": 0,
            "point_group": null
        },
        {
            "id": 73124,
            "label_id": 613,
            "x_pos": -8979.5,
            "y_pos": 3914,
            "author_name": "elevenium",
            "ctime": "2024-09-05 10:57:51",
            "display_state": 1,
            "area_id": 11,
            "ext_attrs": "{}",
            "ext_attrs_map": {},
            "z_level": 0,
            "icon_sign": 0,
            "point_group": null
        },
        {
            "id": 73123,
            "label_id": 613,
            "x_pos": -8971,
            "y_pos": 3964.5,
            "author_name": "elevenium",
            "ctime": "2024-09-05 10:57:53",
            "display_state": 1,
            "area_id": 11,
            "ext_attrs": "{}",
            "ext_attrs_map": {},
            "z_level": 0,
            "icon_sign": 0,
            "point_group": null
        },
        {
            "id": 73122,
            "label_id": 613,
            "x_pos": -8667.25,
            "y_pos": 3719.25,
            "author_name": "elevenium",
            "ctime": "2024-08-28 22:29:16",
            "display_state": 1,
            "area_id": 11,
            "ext_attrs": "{}",
            "ext_attrs_map": {},
            "z_level": 0,
            "icon_sign": 0,
            "point_group": null
        },
        {
            "id": 73121,
            "label_id": 613,
            "x_pos": -8679.5,
            "y_pos": 3728,
            "author_name": "elevenium",
            "ctime": "2024-08-28 22:29:12",
            "display_state": 1,
            "area_id": 11,
            "ext_attrs": "{}",
            "ext_attrs_map": {},
            "z_level": 0,
            "icon_sign": 0,
            "point_group": null
        },
        {
            "id": 73120,
            "label_id": 613,
            "x_pos": -8718,
            "y_pos": 3748,
            "author_name": "elevenium",
            "ctime": "2024-08-28 22:29:05",
            "display_state": 1,
            "area_id": 11,
            "ext_attrs": "{}",
            "ext_attrs_map": {},
            "z_level": 0,
            "icon_sign": 0,
            "point_group": null
        },
        {
            "id": 73119,
            "label_id": 613,
            "x_pos": -8710.5,
            "y_pos": 3744.5,
            "author_name": "elevenium",
            "ctime": "2024-08-28 22:29:08",
            "display_state": 1,
            "area_id": 11,
            "ext_attrs": "{}",
            "ext_attrs_map": {},
            "z_level": 0,
            "icon_sign": 0,
            "point_group": null
        },
        {
            "id": 73118,
            "label_id": 613,
            "x_pos": -8847.5,
            "y_pos": 3859.5,
            "author_name": "elevenium",
            "ctime": "2024-09-05 10:57:47",
            "display_state": 1,
            "area_id": 11,
            "ext_attrs": "{}",
            "ext_attrs_map": {},
            "z_level": 0,
            "icon_sign": 0,
            "point_group": null
        },
        {
            "id": 73117,
            "label_id": 613,
            "x_pos": -8848.75,
            "y_pos": 3861.75,
            "author_name": "elevenium",
            "ctime": "2024-09-05 10:57:41",
            "display_state": 1,
            "area_id": 11,
            "ext_attrs": "{}",
            "ext_attrs_map": {},
            "z_level": 0,
            "icon_sign": 0,
            "point_group": null
        },
        {
            "id": 73116,
            "label_id": 613,
            "x_pos": -8849,
            "y_pos": 3864.5,
            "author_name": "elevenium",
            "ctime": "2024-09-05 10:57:59",
            "display_state": 1,
            "area_id": 11,
            "ext_attrs": "{}",
            "ext_attrs_map": {},
            "z_level": 0,
            "icon_sign": 0,
            "point_group": null
        },
        {
            "id": 73115,
            "label_id": 613,
            "x_pos": -8868.5,
            "y_pos": 3872,
            "author_name": "elevenium",
            "ctime": "2024-09-05 10:57:56",
            "display_state": 1,
            "area_id": 11,
            "ext_attrs": "{}",
            "ext_attrs_map": {},
            "z_level": 0,
            "icon_sign": 0,
            "point_group": null
        },
        {
            "id": 73114,
            "label_id": 613,
            "x_pos": -8871.5,
            "y_pos": 3870,
            "author_name": "elevenium",
            "ctime": "2024-09-05 10:57:45",
            "display_state": 1,
            "area_id": 11,
            "ext_attrs": "{}",
            "ext_attrs_map": {},
            "z_level": 0,
            "icon_sign": 0,
            "point_group": null
        },
        {
            "id": 73113,
            "label_id": 613,
            "x_pos": -8867,
            "y_pos": 3847,
            "author_name": "elevenium",
            "ctime": "2024-09-05 10:57:49",
            "display_state": 1,
            "area_id": 11,
            "ext_attrs": "{}",
            "ext_attrs_map": {},
            "z_level": 0,
            "icon_sign": 0,
            "point_group": null
        },
        {
            "id": 73112,
            "label_id": 613,
            "x_pos": -8893,
            "y_pos": 3745,
            "author_name": "elevenium",
            "ctime": "2024-09-05 10:57:51",
            "display_state": 1,
            "area_id": 11,
            "ext_attrs": "{}",
            "ext_attrs_map": {},
            "z_level": 0,
            "icon_sign": 0,
            "point_group": null
        },
        {
            "id": 73111,
            "label_id": 613,
            "x_pos": -8890,
            "y_pos": 3741.5,
            "author_name": "elevenium",
            "ctime": "2024-09-05 10:57:51",
            "display_state": 1,
            "area_id": 11,
            "ext_attrs": "{}",
            "ext_attrs_map": {},
            "z_level": 0,
            "icon_sign": 0,
            "point_group": null
        },
        {
            "id": 73110,
            "label_id": 613,
            "x_pos": -8865,
            "y_pos": 3725.5,
            "author_name": "elevenium",
            "ctime": "2024-09-05 10:57:58",
            "display_state": 1,
            "area_id": 11,
            "ext_attrs": "{}",
            "ext_attrs_map": {},
            "z_level": 0,
            "icon_sign": 0,
            "point_group": null
        },
        {
            "id": 73109,
            "label_id": 613,
            "x_pos": -8864,
            "y_pos": 3722.5,
            "author_name": "elevenium",
            "ctime": "2024-09-05 10:57:57",
            "display_state": 1,
            "area_id": 11,
            "ext_attrs": "{}",
            "ext_attrs_map": {},
            "z_level": 0,
            "icon_sign": 0,
            "point_group": null
        },
        {
            "id": 73108,
            "label_id": 613,
            "x_pos": -8856,
            "y_pos": 3707.5,
            "author_name": "elevenium",
            "ctime": "2024-09-05 10:57:58",
            "display_state": 1,
            "area_id": 11,
            "ext_attrs": "{}",
            "ext_attrs_map": {},
            "z_level": 0,
            "icon_sign": 0,
            "point_group": null
        },
        {
            "id": 73107,
            "label_id": 613,
            "x_pos": -8831.25,
            "y_pos": 3707,
            "author_name": "elevenium",
            "ctime": "2024-09-05 10:57:52",
            "display_state": 1,
            "area_id": 11,
            "ext_attrs": "{}",
            "ext_attrs_map": {},
            "z_level": 0,
            "icon_sign": 0,
            "point_group": null
        },
        {
            "id": 73106,
            "label_id": 613,
            "x_pos": -8830.25,
            "y_pos": 3705.5,
            "author_name": "elevenium",
            "ctime": "2024-09-05 10:57:53",
            "display_state": 1,
            "area_id": 11,
            "ext_attrs": "{}",
            "ext_attrs_map": {},
            "z_level": 0,
            "icon_sign": 0,
            "point_group": null
        },
        {
            "id": 73105,
            "label_id": 613,
            "x_pos": -8803.5,
            "y_pos": 3717.5,
            "author_name": "elevenium",
            "ctime": "2024-09-05 10:57:41",
            "display_state": 1,
            "area_id": 11,
            "ext_attrs": "{}",
            "ext_attrs_map": {},
            "z_level": 0,
            "icon_sign": 0,
            "point_group": null
        },
        {
            "id": 73104,
            "label_id": 613,
            "x_pos": -8792.5,
            "y_pos": 3674,
            "author_name": "elevenium",
            "ctime": "2024-08-28 22:29:19",
            "display_state": 1,
            "area_id": 11,
            "ext_attrs": "{}",
            "ext_attrs_map": {},
            "z_level": 0,
            "icon_sign": 0,
            "point_group": null
        },
        {
            "id": 73103,
            "label_id": 613,
            "x_pos": -8798.5,
            "y_pos": 3676,
            "author_name": "elevenium",
            "ctime": "2024-08-28 22:29:05",
            "display_state": 1,
            "area_id": 11,
            "ext_attrs": "{}",
            "ext_attrs_map": {},
            "z_level": 0,
            "icon_sign": 0,
            "point_group": null
        },
        {
            "id": 73102,
            "label_id": 613,
            "x_pos": -8725.5,
            "y_pos": 3617.5,
            "author_name": "elevenium",
            "ctime": "2024-08-28 22:29:13",
            "display_state": 1,
            "area_id": 11,
            "ext_attrs": "{}",
            "ext_attrs_map": {},
            "z_level": 0,
            "icon_sign": 0,
            "point_group": null
        },
        {
            "id": 73101,
            "label_id": 613,
            "x_pos": -8728.5,
            "y_pos": 3618.75,
            "author_name": "elevenium",
            "ctime": "2024-08-28 22:29:19",
            "display_state": 1,
            "area_id": 11,
            "ext_attrs": "{}",
            "ext_attrs_map": {},
            "z_level": 0,
            "icon_sign": 0,
            "point_group": null
        },
        {
            "id": 73100,
            "label_id": 613,
            "x_pos": -8665,
            "y_pos": 3614.75,
            "author_name": "elevenium",
            "ctime": "2024-08-28 22:29:15",
            "display_state": 1,
            "area_id": 11,
            "ext_attrs": "{}",
            "ext_attrs_map": {},
            "z_level": 0,
            "icon_sign": 0,
            "point_group": null
        },
        {
            "id": 73099,
            "label_id": 613,
            "x_pos": -8656,
            "y_pos": 3613.75,
            "author_name": "elevenium",
            "ctime": "2024-08-28 22:29:15",
            "display_state": 1,
            "area_id": 11,
            "ext_attrs": "{}",
            "ext_attrs_map": {},
            "z_level": 0,
            "icon_sign": 0,
            "point_group": null
        },
        {
            "id": 73098,
            "label_id": 613,
            "x_pos": -8464.75,
            "y_pos": 4172.25,
            "author_name": "elevenium",
            "ctime": "2024-09-06 13:41:12",
            "display_state": 1,
            "area_id": 11,
            "ext_attrs": "{}",
            "ext_attrs_map": {},
            "z_level": 0,
            "icon_sign": 0,
            "point_group": null
        },
        {
            "id": 73097,
            "label_id": 613,
            "x_pos": -8463.5,
            "y_pos": 4173.25,
            "author_name": "elevenium",
            "ctime": "2024-09-06 13:41:15",
            "display_state": 1,
            "area_id": 11,
            "ext_attrs": "{}",
            "ext_attrs_map": {},
            "z_level": 0,
            "icon_sign": 0,
            "point_group": null
        },
        {
            "id": 73096,
            "label_id": 613,
            "x_pos": -8455.75,
            "y_pos": 4167.5,
            "author_name": "elevenium",
            "ctime": "2024-09-06 13:41:05",
            "display_state": 1,
            "area_id": 11,
            "ext_attrs": "{}",
            "ext_attrs_map": {},
            "z_level": 0,
            "icon_sign": 0,
            "point_group": null
        },
        {
            "id": 73095,
            "label_id": 613,
            "x_pos": -8432.75,
            "y_pos": 4174.5,
            "author_name": "elevenium",
            "ctime": "2024-09-06 13:41:03",
            "display_state": 1,
            "area_id": 11,
            "ext_attrs": "{}",
            "ext_attrs_map": {},
            "z_level": 0,
            "icon_sign": 0,
            "point_group": null
        },
        {
            "id": 73094,
            "label_id": 613,
            "x_pos": -8525.75,
            "y_pos": 3935,
            "author_name": "elevenium",
            "ctime": "2024-09-06 13:41:01",
            "display_state": 1,
            "area_id": 11,
            "ext_attrs": "{}",
            "ext_attrs_map": {},
            "z_level": 0,
            "icon_sign": 0,
            "point_group": null
        },
        {
            "id": 73093,
            "label_id": 613,
            "x_pos": -8524.75,
            "y_pos": 3933,
            "author_name": "elevenium",
            "ctime": "2024-09-06 13:41:14",
            "display_state": 1,
            "area_id": 11,
            "ext_attrs": "{}",
            "ext_attrs_map": {},
            "z_level": 0,
            "icon_sign": 0,
            "point_group": null
        },
        {
            "id": 73092,
            "label_id": 613,
            "x_pos": -8475.5,
            "y_pos": 3924,
            "author_name": "elevenium",
            "ctime": "2024-09-06 13:40:58",
            "display_state": 1,
            "area_id": 11,
            "ext_attrs": "{}",
            "ext_attrs_map": {},
            "z_level": 0,
            "icon_sign": 0,
            "point_group": null
        },
        {
            "id": 73091,
            "label_id": 613,
            "x_pos": -8482.5,
            "y_pos": 3921.5,
            "author_name": "elevenium",
            "ctime": "2024-09-06 13:41:02",
            "display_state": 1,
            "area_id": 11,
            "ext_attrs": "{}",
            "ext_attrs_map": {},
            "z_level": 0,
            "icon_sign": 0,
            "point_group": null
        },
        {
            "id": 73090,
            "label_id": 613,
            "x_pos": -8480.25,
            "y_pos": 3919.75,
            "author_name": "elevenium",
            "ctime": "2024-09-06 13:40:59",
            "display_state": 1,
            "area_id": 11,
            "ext_attrs": "{}",
            "ext_attrs_map": {},
            "z_level": 0,
            "icon_sign": 0,
            "point_group": null
        },
        {
            "id": 73089,
            "label_id": 613,
            "x_pos": -8463.25,
            "y_pos": 3878.75,
            "author_name": "elevenium",
            "ctime": "2024-08-30 14:16:42",
            "display_state": 1,
            "area_id": 11,
            "ext_attrs": "{}",
            "ext_attrs_map": {},
            "z_level": 0,
            "icon_sign": 0,
            "point_group": null
        },
        {
            "id": 73088,
            "label_id": 613,
            "x_pos": -8468.75,
            "y_pos": 3875,
            "author_name": "elevenium",
            "ctime": "2024-08-30 14:16:43",
            "display_state": 1,
            "area_id": 11,
            "ext_attrs": "{}",
            "ext_attrs_map": {},
            "z_level": 0,
            "icon_sign": 0,
            "point_group": null
        },
        {
            "id": 73087,
            "label_id": 613,
            "x_pos": -8519.5,
            "y_pos": 3876.75,
            "author_name": "elevenium",
            "ctime": "2024-08-30 14:16:42",
            "display_state": 1,
            "area_id": 11,
            "ext_attrs": "{}",
            "ext_attrs_map": {},
            "z_level": 0,
            "icon_sign": 0,
            "point_group": null
        },
        {
            "id": 73086,
            "label_id": 613,
            "x_pos": -8508,
            "y_pos": 3879,
            "author_name": "elevenium",
            "ctime": "2024-08-30 14:16:44",
            "display_state": 1,
            "area_id": 11,
            "ext_attrs": "{}",
            "ext_attrs_map": {},
            "z_level": 0,
            "icon_sign": 0,
            "point_group": null
        },
        {
            "id": 73085,
            "label_id": 613,
            "x_pos": -8503.75,
            "y_pos": 3879.25,
            "author_name": "elevenium",
            "ctime": "2024-08-30 14:16:43",
            "display_state": 1,
            "area_id": 11,
            "ext_attrs": "{}",
            "ext_attrs_map": {},
            "z_level": 0,
            "icon_sign": 0,
            "point_group": null
        },
        {
            "id": 73084,
            "label_id": 613,
            "x_pos": -8494,
            "y_pos": 3824,
            "author_name": "elevenium",
            "ctime": "2024-09-06 13:41:02",
            "display_state": 1,
            "area_id": 11,
            "ext_attrs": "{}",
            "ext_attrs_map": {},
            "z_level": 0,
            "icon_sign": 0,
            "point_group": null
        },
        {
            "id": 73083,
            "label_id": 613,
            "x_pos": -8484,
            "y_pos": 3813.5,
            "author_name": "elevenium",
            "ctime": "2024-09-06 13:41:08",
            "display_state": 1,
            "area_id": 11,
            "ext_attrs": "{}",
            "ext_attrs_map": {},
            "z_level": 0,
            "icon_sign": 0,
            "point_group": null
        },
        {
            "id": 73082,
            "label_id": 613,
            "x_pos": -8448,
            "y_pos": 3819.5,
            "author_name": "elevenium",
            "ctime": "2024-09-06 13:41:13",
            "display_state": 1,
            "area_id": 11,
            "ext_attrs": "{}",
            "ext_attrs_map": {},
            "z_level": 0,
            "icon_sign": 0,
            "point_group": null
        }
    ]
}